dmidecode/__init__.py
dmidecode/decode.py
dmidecode/parse.py
dmidecode/parse_test.py
dmidecode/tests/fixtures/dmidecode.txt
py_dmidecode-0.1.3.dist-info/LICENSE
py_dmidecode-0.1.3.dist-info/METADATA
py_dmidecode-0.1.3.dist-info/WHEEL
py_dmidecode-0.1.3.dist-info/RECORD
