Metadata-Version: 2.1
Name: py-dmidecode
Version: 0.1.3
Summary: python library to parse the output of dmidecode
Home-page: https://github.com/zaibon/py-dmidecode
Keywords: system development
Author: Christophe de Carvalho
Author-email: christophe.dcpm@gmail.com
Requires-Python: >=3.8.1,<4.0
Classifier: Development Status :: 3 - Alpha
Classifier: Intended Audience :: Developers
Classifier: License :: OSI Approved :: Apache Software License
Classifier: Programming Language :: Python :: 3
Classifier: Programming Language :: Python :: 3.9
Classifier: Programming Language :: Python :: 3.10
Classifier: Programming Language :: Python :: 3.11
Classifier: Programming Language :: Python :: 3.12
Classifier: Programming Language :: Python :: 3.8
Classifier: Topic :: Software Development :: Libraries :: Python Modules
Project-URL: Bug Tracker, https://github.com/zaibon/py-dmidecode/issues
Project-URL: Repository, https://github.com/zaibon/py-dmidecode
